easyssp_simulation/__init__.py
easyssp_simulation/client/__init__.py
easyssp_simulation/client/py.typed
easyssp_simulation/client/simulation_client.py
easyssp_simulation/models/__init__.py
easyssp_simulation/models/hardware_option.py
easyssp_simulation/models/py.typed
easyssp_simulation/models/run.py
easyssp_simulation/models/simulation.py
easyssp_simulation/models/simulation_info.py
easyssp_simulation/models/simulation_started.py
easyssp_simulation/models/start_simulation_configuration.py
easyssp_simulation/models/start_simulation_run_configuration.py
easyssp_simulation/models/step.py
easyssp_simulation_client-1.0.0.dist-info/METADATA
easyssp_simulation_client-1.0.0.dist-info/WHEEL
easyssp_simulation_client-1.0.0.dist-info/licenses/LICENSE
easyssp_simulation_client-1.0.0.dist-info/RECORD
