Metadata-Version: 2.4
Name: easyssp-simulation-client
Version: 1.0.0
Summary: A Python client for simulating System Structure and Parameterization (SSP) models with integrated Functional Mock-up Interface (FMI) components in easySSP.
Project-URL: Homepage, https://www.easy-ssp.com
Project-URL: Release Changelog, https://github.com/exxcellent/easyssp-simulation-client-python/releases
Project-URL: Source, https://github.com/exxcellent/easyssp-simulation-client-python
Author-email: easySSP Dev Team <easyssp-dev@exxcellent.de>
License: MIT
License-File: LICENSE
Keywords: client,easySSP,python,simulation
Classifier: License :: OSI Approved :: MIT License
Classifier: Operating System :: OS Independent
Classifier: Programming Language :: Python :: 3.11
Requires-Python: >=3.11
Requires-Dist: easyssp-utils>=1.0.0
Requires-Dist: pydantic>=2.11.3
